BuoyanText/TextNorm.py
BuoyanText/TextReader.py
BuoyanText/__init__.py
BuoyanText/data/norm/contractions_English.json
BuoyanText/data/norm/punctuation_Chinese.json
BuoyanText/data/norm/stopwords_Chinese.json
BuoyanText/data/norm/stopwords_English.json
BuoyanText-0.0.5.dist-info/LICENSE
BuoyanText-0.0.5.dist-info/METADATA
BuoyanText-0.0.5.dist-info/WHEEL
BuoyanText-0.0.5.dist-info/top_level.txt
BuoyanText-0.0.5.dist-info/RECORD
