Metadata-Version: 2.1
Name: BuoyanText
Version: 0.0.5
Summary: Normalizing English and Chinese Text
Home-page: https://github.com/BuoyantXu/BuoyantText
Author: Boyang Xu
Author-email: by24225@163.com
Project-URL: Bug Tracker, https://github.com/BuoyantXu/BuoyantText/issues
Classifier: Programming Language :: Python :: 3
Classifier: License :: OSI Approved :: MIT License
Classifier: Operating System :: OS Independent
Classifier: Natural Language :: Chinese (Simplified)
Requires-Python: >=3.7
License-File: LICENSE
Requires-Dist: setuptools (>=61.0)
Requires-Dist: pymupdf
Requires-Dist: pandas
Requires-Dist: nltk
Requires-Dist: jieba
Requires-Dist: spacy
Requires-Dist: bs4
